odoo10_addon_web_search_with_and-10.0.1.0.0-py2.7-nspkg.pth
odoo/addons/web_search_with_and/__manifest__.py
odoo/addons/web_search_with_and/__init__.py
odoo/addons/web_search_with_and/README.rst
odoo/addons/web_search_with_and/data/data.xml
odoo/addons/web_search_with_and/static/description/icon.png
odoo/addons/web_search_with_and/static/src/js/search.js
odoo10_addon_web_search_with_and-10.0.1.0.0.dist-info/top_level.txt
odoo10_addon_web_search_with_and-10.0.1.0.0.dist-info/WHEEL
odoo10_addon_web_search_with_and-10.0.1.0.0.dist-info/RECORD
odoo10_addon_web_search_with_and-10.0.1.0.0.dist-info/metadata.json
odoo10_addon_web_search_with_and-10.0.1.0.0.dist-info/DESCRIPTION.rst
odoo10_addon_web_search_with_and-10.0.1.0.0.dist-info/METADATA
odoo10_addon_web_search_with_and-10.0.1.0.0.dist-info/namespace_packages.txt
