Metadata-Version: 2.0
Name: odoo10-addon-web-search-with-and
Version: 10.0.1.0.0
Summary: Use AND conditions on omnibar search
Home-page: http://www.versada.lt
Author: Versada UAB, Odoo Community Association (OCA)
Author-email: support@odoo-community.org
License: AGPL-3
Platform: UNKNOWN
Requires-Dist: odoo (<10.1dev,>=10.0)
Classifier: Programming Language :: Python :: 2.7
Classifier: Framework :: Odoo
Classifier: License :: OSI Approved :: GNU Affero General Public License v3
